requests_sap/__init__.py
requests_sap/sap.py
requests_sap-0.0.6.dist-info/LICENSE
requests_sap-0.0.6.dist-info/METADATA
requests_sap-0.0.6.dist-info/WHEEL
requests_sap-0.0.6.dist-info/top_level.txt
requests_sap-0.0.6.dist-info/RECORD
