Metadata-Version: 2.1
Name: requests-sap
Version: 0.0.6
Summary: Plugin for SAP launchapd in for python requests
Author-email: Ondra Machacek <machacek.ondra@gmail.com>
License: Copyright (c) 2018 The Python Packaging Authority        
Project-URL: Homepage, https://github.com/machacekondra/requests-sap
Project-URL: Bug Tracker, https://github.com/machacekondra/requests-sap/issues
Classifier: Programming Language :: Python :: 3
Classifier: License :: OSI Approved :: MIT License
Classifier: Operating System :: OS Independent
Requires-Python: >=3.7
License-File: LICENSE
Requires-Dist: requests
Requires-Dist: lxml
